Metadata-Version: 2.4
Name: llm-fragments-reader
Version: 0.1
Summary: Run URLs through the Jina Reader API
Author: Simon Willison
License-Expression: Apache-2.0
Project-URL: Homepage, https://github.com/simonw/llm-fragments-reader
Project-URL: Changelog, https://github.com/simonw/llm-fragments-reader/releases
Project-URL: Issues, https://github.com/simonw/llm-fragments-reader/issues
Project-URL: CI, https://github.com/simonw/llm-fragments-reader/actions
Requires-Python: >=3.9
License-File: LICENSE
Requires-Dist: llm
Provides-Extra: test
Requires-Dist: pytest; extra == "test"
Requires-Dist: pytest-httpx; extra == "test"
Dynamic: license-file
